<Alloy>
	<View class="container" saveableContainer="true" backgroundColor="white" width="100%" height="100%">
		<Widget id="titleBar" src="com.hoyoji.titanium.widget.TitleBar"
				 addModeTitle="注册用户" readModeTitle="用户资料" editModeTitle="修改用户"/>
			  <TableView id="table" class="table-edit" bottom="0" top="42">
                <TableViewRow class="table-edit-row">
                	<Widget src="com.hoyoji.titanium.widget.AutoUpdatableTextField" labelText="用户名" hintText="请输入用户名" 
                		editModeEditability="noneditable"
                		bindModel="$.$model"
                		bindAttribute="userName"/>
                </TableViewRow>
                <TableViewRow class="table-row-edit">
                	<Widget src="com.hoyoji.titanium.widget.AutoUpdatableTextField" labelText="密码" hintText="请输入密码" passwordMask="true"
                		bindModel="$.$model"
                		bindAttribute="password"/>
                </TableViewRow>
                <TableViewRow class="table-row-edit">
                	<Widget src="com.hoyoji.titanium.widget.AutoUpdatableTextField" labelText="确认密码" hintText="请再次输入密码" passwordMask="true"
                		bindModel="$.$model"
                		bindAttribute="password2"/>
                </TableViewRow>
           </TableView>
	</View>
</Alloy>